MANIFEST.in
README.rst
setup.py
brzipcode/__init__.py
brzipcode/main.py
brzipcode/models.py
brzipcode/tests.py
brzipcode/urls.py
brzipcode/views.py
brzipcode.egg-info/PKG-INFO
brzipcode.egg-info/SOURCES.txt
brzipcode.egg-info/dependency_links.txt
brzipcode.egg-info/not-zip-safe
brzipcode.egg-info/requires.txt
brzipcode.egg-info/top_level.txt