Metadata-Version: 1.1
Name: brzipcode
Version: 0.1.2
Summary: brzipcode is a lightweight app for retrieving brazilian addresses from a zip code
Home-page: http://github.com/rpedigoni/brzipcode
Author: Renato Pedigoni
Author-email: renatopedigoni@gmail.com
License: BSD
Keywords: zip code
Platform: UNKNOWN
Classifier: Programming Language :: Python
Classifier: Topic :: Software Development :: Libraries :: Python Modules
Classifier: Framework :: Django
